jlvandenhout/graph/__init__.py
jlvandenhout/graph/algorithms.py
jlvandenhout/graph/core.py
jlvandenhout_graph-2.1.0.dist-info/LICENSE
jlvandenhout_graph-2.1.0.dist-info/METADATA
jlvandenhout_graph-2.1.0.dist-info/WHEEL
jlvandenhout_graph-2.1.0.dist-info/top_level.txt
jlvandenhout_graph-2.1.0.dist-info/RECORD
