Metadata-Version: 2.1
Name: jlvandenhout-graph
Version: 2.1.0
Summary: This package provides a simple graph implementation for Python.
Home-page: https://gitlab.com/jlvandenhout/graph
Author: J.L. van den Hout
License: UNKNOWN
Platform: UNKNOWN
Classifier: License :: OSI Approved :: GNU General Public License v3 (GPLv3)
Classifier: Operating System :: OS Independent
Classifier: Programming Language :: Python :: 3
